mouse_tracking/__init__.py
mouse_tracking/cli/__init__.py
mouse_tracking/cli/infer.py
mouse_tracking/cli/main.py
mouse_tracking/cli/qa.py
mouse_tracking/cli/utils.py
mouse_tracking/core/__init__.py
mouse_tracking/core/exceptions.py
mouse_tracking/core/config/__init__.py
mouse_tracking/core/config/config.py
mouse_tracking/core/config/pose_utils.py
mouse_tracking/matching/__init__.py
mouse_tracking/matching/batch_processing.py
mouse_tracking/matching/core.py
mouse_tracking/matching/detection.py
mouse_tracking/matching/greedy_matching.py
mouse_tracking/matching/match_predictions.py
mouse_tracking/matching/vectorized_features.py
mouse_tracking/models/__init__.py
mouse_tracking/models/model_definitions.py
mouse_tracking/pose/__init__.py
mouse_tracking/pose/convert.py
mouse_tracking/pose/inspect.py
mouse_tracking/pose/render.py
mouse_tracking/pytorch_inference/__init__.py
mouse_tracking/pytorch_inference/fecal_boli.py
mouse_tracking/pytorch_inference/multi_pose.py
mouse_tracking/pytorch_inference/single_pose.py
mouse_tracking/pytorch_inference/hrnet/__init__.py
mouse_tracking/pytorch_inference/hrnet/config/__init__.py
mouse_tracking/pytorch_inference/hrnet/config/default.py
mouse_tracking/pytorch_inference/hrnet/config/models.py
mouse_tracking/pytorch_inference/hrnet/models/__init__.py
mouse_tracking/pytorch_inference/hrnet/models/pose_hrnet.py
mouse_tracking/support/__init__.py
mouse_tracking/tfs_inference/__init__.py
mouse_tracking/tfs_inference/arena_corners.py
mouse_tracking/tfs_inference/food_hopper.py
mouse_tracking/tfs_inference/lixit.py
mouse_tracking/tfs_inference/multi_identity.py
mouse_tracking/tfs_inference/multi_segmentation.py
mouse_tracking/tfs_inference/single_segmentation.py
mouse_tracking/utils/__init__.py
mouse_tracking/utils/arrays.py
mouse_tracking/utils/clip_video.py
mouse_tracking/utils/features.py
mouse_tracking/utils/fecal_boli.py
mouse_tracking/utils/hashing.py
mouse_tracking/utils/hrnet.py
mouse_tracking/utils/identity.py
mouse_tracking-0.2.4.dist-info/METADATA
mouse_tracking-0.2.4.dist-info/WHEEL
mouse_tracking-0.2.4.dist-info/entry_points.txt
mouse_tracking-0.2.4.dist-info/licenses/LICENSE
mouse_tracking-0.2.4.dist-info/RECORD
