Metadata-Version: 2.4
Name: mouse-tracking
Version: 0.2.4
Summary: Runtime environment for mouse tracking experiments
License-File: LICENSE
Requires-Python: <3.11,>=3.10
Requires-Dist: absl-py==1.4.0
Requires-Dist: h5py>=3.11.0
Requires-Dist: imageio[ffmpeg]==2.31.6
Requires-Dist: matplotlib==3.7.1
Requires-Dist: networkx==3.3
Requires-Dist: numpy<2.2.0,>=1.26.0
Requires-Dist: opencv-python-headless==4.8.0.76
Requires-Dist: pandas==2.0.3
Requires-Dist: pillow==9.4.0
Requires-Dist: plotnine>=0.12.0
Requires-Dist: pydantic-settings>=2.10.1
Requires-Dist: pydantic==2.7.4
Requires-Dist: scipy==1.11.4
Requires-Dist: typer>=0.12.4
Requires-Dist: yacs>=0.1.8
Provides-Extra: cpu
Requires-Dist: tensorflow==2.20.0; extra == 'cpu'
Requires-Dist: torch==2.6.0; extra == 'cpu'
Requires-Dist: torchaudio==2.6.0; extra == 'cpu'
Requires-Dist: torchvision==0.21.0; extra == 'cpu'
Provides-Extra: gpu
Requires-Dist: nvidia-cusparselt-cu12==0.6.3; extra == 'gpu'
Requires-Dist: tensorflow[and-cuda]==2.20.0; extra == 'gpu'
Requires-Dist: torch==2.6.0; extra == 'gpu'
Requires-Dist: torchaudio==2.6.0; extra == 'gpu'
Requires-Dist: torchvision==0.21.0; extra == 'gpu'
